markdown_meta_extension/__init__.py
markdown_meta_extension/importing.py
markdown_meta_extension/plugins/__init__.py
markdown_meta_extension/plugins/file_system_plugin.py
markdown_meta_extension/plugins/jinja_template_plugin.py
markdown_meta_extension/plugins/module_plugin.py
markdown_meta_extension/plugins/package_plugin.py
markdown_meta_extension/plugins/spec.py
markdown_meta_extension-0.5.3.dist-info/LICENSE.md
markdown_meta_extension-0.5.3.dist-info/METADATA
markdown_meta_extension-0.5.3.dist-info/WHEEL
markdown_meta_extension-0.5.3.dist-info/entry_points.txt
markdown_meta_extension-0.5.3.dist-info/top_level.txt
markdown_meta_extension-0.5.3.dist-info/RECORD
