Metadata-Version: 2.1
Name: markdown-meta-extension
Version: 0.5.3
Summary: Markdown Meta Extension for using Python functions and classes from within documents.
Home-page: https://gitlab.com/markdown-meta-extension/markdown-meta-extension
Author: Martin Schorfmann
Author-email: schorfma@uni-bremen.de
License: MIT
Platform: UNKNOWN
Classifier: Programming Language :: Python
Classifier: Programming Language :: Python :: 3
Classifier: Programming Language :: Python :: 3.7
Classifier: Programming Language :: Python :: 3.8
Classifier: Topic :: Text Processing :: Markup
Classifier: License :: OSI Approved :: MIT License
Requires-Python: >=3.7.0
Requires-Dist: Click
Requires-Dist: jinja2
Requires-Dist: Markdown
Requires-Dist: MarkupSafe
Requires-Dist: pathvalidate
Requires-Dist: PyYAML
Provides-Extra: pelican
Requires-Dist: pelican ; extra == 'pelican'
